Metadata-Version: 2.1
Name: hsvpicker
Version: 4.0
Summary: Finding HSV bounding values for tracking/masking an object.
Home-page: https://github.com/Karthikprabuvetrivel/hsvpicker
Author: Karthik Prabu V
Author-email: sanjkar13@gmail.com
License: MIT
Download-URL: https://github.com/Karthikprabuvetrivel/hsvpicker/archive/v4.0.tar.gz
Keywords: hsv,opencv,cv2,mask,track,object,images,videos
Platform: UNKNOWN
Classifier: Development Status :: 3 - Alpha
Classifier: Intended Audience :: Developers
Classifier: Topic :: Software Development :: Build Tools
Classifier: License :: OSI Approved :: MIT License
Classifier: Programming Language :: Python :: 3
Classifier: Programming Language :: Python :: 3.4
Classifier: Programming Language :: Python :: 3.5
Classifier: Programming Language :: Python :: 3.6
